MANIFEST.in
Makefile
README.md
bignum.cpp
bignum.h
cmdline.cpp
compiler.cpp
compiler.h
example.cpp
f.py
funcs.cpp
funcs.h
functions.cpp
functions.h
keccak-tiny-wrapper.h
keccak-tiny.cpp
keccak-tiny.h
lllparser.cpp
lllparser.h
opcodes.cpp
opcodes.h
optimize.cpp
optimize.h
parser.cpp
parser.h
preprocess.cpp
preprocess.h
pyserpent.cpp
pyserpent.py
rewriter.cpp
rewriter.h
rewriteutils.cpp
rewriteutils.h
serpent.py
setup.py
tokenize.cpp
tokenize.h
util.cpp
util.h
ethereum_serpent.egg-info/PKG-INFO
ethereum_serpent.egg-info/SOURCES.txt
ethereum_serpent.egg-info/dependency_links.txt
ethereum_serpent.egg-info/entry_points.txt
ethereum_serpent.egg-info/top_level.txt