Metadata-Version: 1.0
Name: ethereum-serpent
Version: 2.0.1
Summary: Serpent compiler
Home-page: http://www.ethereum.org/
Author: Vitalik Buterin
Author-email: v@buterin.com
License: WTFPL
Platform: UNKNOWN
